{
  "title": "ویژگی‌های جغرافیایی اردستان",
  "location": {
    "province": "اصفهان",
    "city": "اردستان"
  },
  "geographical_features": [
    {
      "name": "رودخانه‌ها",
      "description": []
    },
    {
      "name": "کوه‌ها",
      "description": [
        {
          "name": "کوه چاه زنگول",
          "images": [""]
        }
      ]
    },
    {
      "name": "دریاچه‌ها",
      "description": []
    },
    {
      "name": "پوشش گیاهی",
      "description": [
        "گیاهان استپی بیابانی",
        "درختچه‌های تاغ و گز"
      ]
    }
  ],
  "topography": [
    {
      "name": "منطقه اقلیمی",
      "description": [
        "تابستان‌های گرم و خشک",
        "زمستان‌های سرد و خشک",
        "نوسانات شدید دمایی بین شب و روز"
      ]
    },
    {
      "name": "ارتفاع",
      "description": [
        "۱٬۲۰۷ متر از سطح دریا"
      ]
    },
    {
      "name": "توپوگرافی",
      "description": [
        "دشت‌های کویری در شمال",
        "کوه‌های زاگرس در جنوب"
      ]
    },
    {
      "name": "ویژگی‌های زمین‌شناسی",
      "description": [
        "سنگ‌های آذرین دوران سوم زمین‌شناسی",
        "وجود معادن سنگ‌های تزئینی"
      ]
    }
  ],
  "natural_resources": [
    {
      "name": "منابع آبی",
      "description": [
        "قنات‌های متعدد از جمله قنات دوطبقه مون",
        "چاه‌های آب زیرزمینی"
      ]
    },
    {
      "name": "منابع معدنی",
      "description": [
        "سنگ‌های تزئینی مانند گرانیت سبز",
        "رس و مصالح ساختمانی"
      ]
    }
  ],
  "tourist_attractions": [
    {
      "name": "مسجد جامع اردستان",
      "images": ["https://api2.kojaro.com/media/2022-9-affd3147-2038-44ee-9c0f-4100021d044a-67c46111c1067c5ba76804c1?w=1680&q=80"],
      "year_built": "دوره سلجوقی",
      "architect": "استاد محمود اصفهانی",
      "constructor": "نامشخص",
      "description": "یکی از قدیمی‌ترین مساجد ایران و نخستین مسجد دوطبقه تاریخ اسلام."
    },
    {
      "name": "قنات دوطبقه مون",
      "images": ["https://media.imna.ir/d/2021/05/31/4/1704257.jpg"],
      "year_built": "حدود ۸۰۰ سال پیش",
      "architect": "نامشخص",
      "constructor": "نامشخص",
      "description": "تنها قنات دوطبقه جهان با دو جریان آب مستقل در طبقات مختلف."
    },
    {
      "name": "مسجد جامع زواره",
      "images": ["https://api2.kojaro.com/media/2022-10-d909a748-0c74-4f59-8c43-c63eedec56dc-67c46112c1067c5ba7680a37?w=1200&q=80"],
      "year_built": "دوره سلجوقی",
      "architect": "نامشخص",
      "constructor": "نامشخص",
      "description": "یکی از مساجد تاریخی با معماری چهار ایوانی و گچ‌بری‌های نفیس."
    },
    {
      "name": "کاخ سرهنگ‌آباد",
      "images": ["https://cdn.isna.ir/d/2018/05/03/4/57674071.jpg"],
      "year_built": "دوره قاجار",
      "architect": "نامشخص",
      "constructor": "مصطفی قلی خان سهام‌السلطنه",
      "description": "کاخی تاریخی با معماری خاص در دهستان سفلا بخش زواره."
    },
    {
      "name": "بازار تاریخی زواره",
      "images": ["https://api2.kojaro.com/media/2022-11-81334511-4266-40e3-8c05-65a3461fa362-67c46112c1067c5ba76811af?w=1200&q=80"],
      "year_built": "دوره قاجار",
      "architect": "محمدحسین عامری",
      "constructor": "نامشخص",
      "description": "بازاری قدیمی با ساختار سنتی و معماری منحصر به فرد."
    },
    {
      "name": "قلعه سنگ بست",
      "images": ["https://cdn.isna.ir/d/2020/11/21/3/61783920.jpg"],
      "year_built": "قرن پنجم هجری قمری",
      "architect": "نامشخص",
      "constructor": "ابوعلی دهدار زواره‌ای",
      "description": "یکی از بزرگ‌ترین و مستحکم‌ترین قلعه‌های تاریخی ایران."
    }
  ],
  "additional_info": {
    "wikipedia_source": [
      "https://fa.wikipedia.org/wiki/اردستان",
      "https://fa.wikipedia.org/wiki/شهرستان_اردستان"
    ],
    "books_source": "http://chap.sch.ir/books/12241"
  }
}
