{
    "title": "ویژگی‌های جغرافیایی شهرستان گناوه",
    "location": {
      "province": "بوشهر",
      "city": "بندر گناوه"
    },
    "geographical_features": [
      {
        "name": "رودخانه‌ها",
        "description": [
          {
            "name": "رودخانه حله",
            "images": []
          }
        ]
      },
      {
        "name": "کوه‌ها",
        "description": [
          {
            "name": "کوه‌های اطراف منطقه",
            "images": []
          }
        ]
      },
      {
        "name": "دریاچه‌ها",
        "description": []
      },
      {
        "name": "پوشش گیاهی",
        "description": [
          "نخلستان‌های گسترده",
          "درختان کنار",
          "درختان کهور",
          "درختان گز"
        ]
      }
    ],
    "topography": [
      {
        "name": "اقلیم",
        "description": [
          "گرم و مرطوب با تابستان‌های بسیار گرم و زمستان‌های معتدل",
          "میانگین بارش سالانه: حدود 150 میلی‌متر"
        ]
      },
      {
        "name": "ارتفاع",
        "description": [
          "میانگین ارتفاع شهرستان: 11 متر از سطح دریا"
        ]
      },
      {
        "name": "توپوگرافی",
        "description": [
          "دشت‌های ساحلی با تپه‌های کم‌ارتفاع و کوه‌های پراکنده"
        ]
      },
      {
        "name": "ویژگی‌های زمین‌شناسی",
        "description": [
          "وجود معادن سنگ آهک و رس",
          "گسل‌های فعال در منطقه"
        ]
      }
    ],
    "natural_resources": [
      {
        "name": "منابع آبی",
        "description": [
          "قنات‌ها و چشمه‌های فصلی",
          "رودخانه حله"
        ]
      },
      {
        "name": "منابع معدنی",
        "description": [
          "سنگ آهک",
          "رس"
        ]
      }
    ],
    "tourist_attractions": [
      {
        "name": "ساحل شنی بندر گناوه",
        "images": [],
        "year_built": "",
        "architect": "",
        "constructor": "",
        "description": "ساحلی زیبا با شن‌های نرم و صدف‌های فراوان، مناسب برای تفریحات آبی و پیاده‌روی."
      },
      {
        "name": "تالاب حله",
        "images": [],
        "year_built": "",
        "architect": "",
        "constructor": "",
        "description": "تالابی طبیعی با مساحت ۴۰ هزار هکتار، زیستگاه پرندگان مهاجر و گونه‌های مختلف گیاهی."
      },
      {
        "name": "تپه‌های باستانی گناوه",
        "images": [],
        "year_built": "دوره‌های مختلف تاریخی",
        "architect": "",
        "constructor": "",
        "description": "تپه‌هایی با قدمت تاریخی، شامل تپه شاه ناصری، تپه قلعه کلات و تپه تل محمد حیدر."
      },
      {
        "name": "جزیره میرمهنا",
        "images": [],
        "year_built": "",
        "architect": "",
        "constructor": "",
        "description": "جزیره‌ای غیرمسکونی با طبیعت بکر، درختان کنار و قدمگاه امیرالمؤمنین."
      },
      {
        "name": "برج خان",
        "images": [],
        "year_built": "حدود ۲۵۰ سال پیش",
        "architect": "",
        "constructor": "خان‌علی‌خان حیات‌داوودی",
        "description": "برجی تاریخی با معماری خاص، محل تصمیم‌گیری‌های سیاسی در گذشته."
      },
      {
        "name": "امامزاده سلیمان بن علی (ع)",
        "images": [],
        "year_built": "دوره قاجاریه و صفویه",
        "architect": "",
        "constructor": "",
        "description": "بقعه‌ای مذهبی با گنبد کاشی‌کاری شده، منسوب به نواده امام سجاد (ع)."
      },
      {
        "name": "دهکده گردشگری مال قائد",
        "images": [],
        "year_built": "",
        "architect": "",
        "constructor": "",
        "description": "روستایی با طبیعت سرسبز، آثار باستانی و امکانات رفاهی، مناسب برای گردشگری."
      },
      {
        "name": "بازار اصلی گناوه",
        "images": [],
        "year_built": "",
        "architect": "",
        "constructor": "",
        "description": "بازاری پررونق با انواع کالاهای ته‌لنجی، مقصدی محبوب برای خرید."
      }
    ],
    "additional_info": {
      "books_source": "http://chap.sch.ir/category/دوره/دوره-آموزش-متوسطه/جغرافیاد-استان-ها"
    }
  }
  