[
    {
        "id": "",
        "context": "بار الها بحق هشت و چهار، شاه عباس را نگهدار. این شعر اولین بیت از کتیبه سنگی رخ شهرکرد است که در زمان شاه عباس دوم صفوی دستور ساخت آن داده شد. گویا شاه عباس دوم پس از سرکشی پروژه اتصال سرچشمه کارون به زاینده رود، دستور ساخت جاده ای را در دامنه کوه رخ می دهد که وجود این کتیبه دلیلی است بر این ادعا.",
        "images": [
            "https://borna.news/files/fa/news/1396/4/18/1039771_452.jpg"
        ]
    },
    {
        "id": "",
        "context": "قلعه خلیل اسفندیاری فرخ‌شهر، مربوط به اواخر دوره قاجار است و در مرکز فرخ‌شهر واقع شده است. مالک آن خلیل اسفندیاری، پدر ثریا اسفندیاری (همسر محمد رضا شاه پهلوی ) است و به نقلی زادگاه ثریا اسفندیاری است.",
        "images": ["https://cdn.balad.ir/crowd-images/all/original/6slQL8GazoobhD-0a08f83a7dbb437db8e95d5523a8debf.jpg"]
    },
    {
        "id": "",
        "context": "منطقه تنگ صیاد ناحیه کوهستانی و مرتفع در استان چهارمحال و بختیاری واقع‌شده ‌است و قله جیلون در محدوده کوه‌های فرخ‌شهر با ۳ هزار و ۱۴۱ متر ارتفاع از سطح دریا، بلندترین نقطه منطقه ‌است. تنگ صیاد به‌واسطه دارا بودن تعداد زیادی تپه‌ماهور زیستگاه مناسبی برای گونه قوچ و میش وحشی است. کوهستان‌های جنوبی منطقه دارای صخره‌های سخت گذر است که زیستگاه پلنگ و کل و بز با جمعیتی قابل‌توجه ‌است.",
        "images": [
            "https://api2.kojaro.com/media/2019-1-ec307cbb-23ad-4c55-9a57-48b7b79a992f-67c460fbc1067c5ba765310d?w=828&q=80",
            "https://api2.kojaro.com/media/2019-1-d8188b79-9da1-4fbf-a790-a63adf697ad9-67c460fbc1067c5ba765310c?w=750&q=80",
            "https://api2.kojaro.com/media/2019-1-d38c061a-cb79-4753-807f-187a4d7b143a-67c460fbc1067c5ba765310b?w=750&q=80",
            "https://api2.kojaro.com/media/2016-7-a01433a9-4d67-46a5-9fea-6f7b9dc74485-67c460c1c1067c5ba75d67db?w=828&q=80",
            "https://api2.kojaro.com/media/2016-7-78ee63fd-2b14-4fea-891a-bc193b6edd2f-67c460c1c1067c5ba75d67de?w=828&q=80"
        ]
    }
]